<annotation>
	<folder>train</folder>
	<filename>sugarcane_014.jpg</filename>
	<path>C:\Users\dell\Desktop\Yash\SIH\Prototype\crop_detection\data\images\train\sugarcane_014.jpg</path>
	<source>
		<database>Unknown</database>
	</source>
	<size>
		<width>1300</width>
		<height>866</height>
		<depth>3</depth>
	</size>
	<segmented>0</segmented>
	<object>
		<name>sugarcane</name>
		<pose>Unspecified</pose>
		<truncated>0</truncated>
		<difficult>0</difficult>
		<bndbox>
			<xmin>2</xmin>
			<ymin>224</ymin>
			<xmax>508</xmax>
			<ymax>841</ymax>
		</bndbox>
	</object>
	<object>
		<name>sugarcane</name>
		<pose>Unspecified</pose>
		<truncated>0</truncated>
		<difficult>0</difficult>
		<bndbox>
			<xmin>8</xmin>
			<ymin>229</ymin>
			<xmax>1121</xmax>
			<ymax>815</ymax>
		</bndbox>
	</object>
	<object>
		<name>sugarcane</name>
		<pose>Unspecified</pose>
		<truncated>0</truncated>
		<difficult>0</difficult>
		<bndbox>
			<xmin>1060</xmin>
			<ymin>381</ymin>
			<xmax>1297</xmax>
			<ymax>716</ymax>
		</bndbox>
	</object>
</annotation>
